funfunc/__init__.py
funfunc/cv.py
funfunc/dl.py
funfunc/ml.py
funfunc/nlp.py
funfunc/others.py
funfunc/tool.py
funfunc-0.2.4.dist-info/LICENSE
funfunc-0.2.4.dist-info/METADATA
funfunc-0.2.4.dist-info/WHEEL
funfunc-0.2.4.dist-info/top_level.txt
funfunc-0.2.4.dist-info/RECORD
